{
    "type": "transactions",
    "attributes": {
        "status": "SETTLED",
        "rawText": "FOODWORKS FERNTR,FERNTREE GULL",
        "description": "Ferntree Gully Supermarket",
        "message": null,
        "isCategorizable": true,
        "holdInfo": {
            "amount": {
                "currencyCode": "AUD",
                "value": "-1.90",
                "valueInBaseUnits": -190
            },
            "foreignAmount": null
        },
        "roundUp": null,
        "cashback": null,
        "amount": {
            "currencyCode": "AUD",
            "value": "-1.90",
            "valueInBaseUnits": -190
        },
        "foreignAmount": null,
        "cardPurchaseMethod": {
            "method": "CONTACTLESS",
            "cardNumberSuffix": "2086"
        },
        "settledAt": "2024-06-04T02:23:26+10:00",
        "createdAt": "2024-06-02T13:20:30+10:00"
    },
    "relationships": {
        "account": {
            "data": {
                "type": "accounts",
                "id": "2de2a86f-236a-4826-980e-12469fc67894"
            },
            "links": {
                "related": "https://api.up.com.au/api/v1/accounts/2de2a86f-236a-4826-980e-12469fc67894"
            }
        },
        "transferAccount": {
            "data": null
        },
        "category": {
            "data": {
                "type": "categories",
                "id": "groceries"
            },
            "links": {
                "self": "https://api.up.com.au/api/v1/transactions/512d69fb-8275-4455-aed3-945cb107d467/relationships/category",
                "related": "https://api.up.com.au/api/v1/categories/groceries"
            }
        },
        "parentCategory": {
            "data": {
                "type": "categories",
                "id": "home"
            },
            "links": {
                "related": "https://api.up.com.au/api/v1/categories/home"
            }
        },
        "tags": {
            "data": [],
            "links": {
                "self": "https://api.up.com.au/api/v1/transactions/512d69fb-8275-4455-aed3-945cb107d467/relationships/tags"
            }
        }
    },
    "links": {
        "self": "https://api.up.com.au/api/v1/transactions/512d69fb-8275-4455-aed3-945cb107d467"
    },
    "_id": "512d69fb-8275-4455-aed3-945cb107d467",
    "createdAt": "2024-06-02T13:20:30+10:00"
}